[
  { "id": 1, "name": "간장", "unit_id": 1, "price": 48.6, "category_id": 10 },
  { "id": 2, "name": "감자", "unit_id": 5, "price": 330, "category_id": 1 },
  { "id": 3, "name": "계란", "unit_id": 5, "price": 133, "category_id": 12 },
  { "id": 4, "name": "고추기름", "unit_id": 1, "price": 92.85, "category_id": 10 },
  { "id": 5, "name": "고추장", "unit_id": 1, "price": 265.8, "category_id": 10 },
  { "id": 6, "name": "국간장", "unit_id": 1, "price": 137.85, "category_id": 10 },
  { "id": 7, "name": "꽈리고추", "unit_id": 3, "price": 13.2, "category_id": 1 },
  { "id": 8, "name": "녹말가루", "unit_id": 1, "price": 64.5, "category_id": 4 },
  { "id": 9, "name": "다진마늘", "unit_id": 1, "price": 138.45, "category_id": 10 },
  { "id": 10, "name": "단호박", "unit_id": 3, "price": 7.75, "category_id": 1 },
  { "id": 11, "name": "달걀", "unit_id": 5, "price": 116.5, "category_id": 12 },
  { "id": 12, "name": "닭가슴살", "unit_id": 3, "price": 12.72, "category_id": 3 },
  { "id": 13, "name": "당근", "unit_id": 5, "price": 1260, "category_id": 1 },
  { "id": 14, "name": "대파", "unit_id": 6, "price": 456, "category_id": 1 },
  { "id": 15, "name": "두부", "unit_id": 7, "price": 3708, "category_id": 6 },
  { "id": 16, "name": "딸기잼", "unit_id": 3, "price": 12.95, "category_id": 9 },
  { "id": 17, "name": "마늘", "unit_id": 8, "price": 60.35, "category_id": 1 },
  { "id": 18, "name": "마요네즈", "unit_id": 1, "price": 633.45, "category_id": 10 },
  { "id": 19, "name": "맛술", "unit_id": 1, "price": 5.55, "category_id": 10 },
  { "id": 20, "name": "멸치", "unit_id": 9, "price": 37.8, "category_id": 5 },
  { "id": 21, "name": "문어", "unit_id": 3, "price": 34.9, "category_id": 8 },
  { "id": 22, "name": "물", "unit_id": 4, "price": 0, "category_id": 10 },
  { "id": 23, "name": "밀가루", "unit_id": 1, "price": 22.05, "category_id": 4 },
  { "id": 24, "name": "바질", "unit_id": 3, "price": 59.7, "category_id": 1 },
  { "id": 25, "name": "박력분", "unit_id": 3, "price": 1.96, "category_id": 4 },
  { "id": 26, "name": "밥", "unit_id": 10, "price": 766, "category_id": 2 },
  { "id": 27, "name": "버터", "unit_id": 3, "price": 24.5, "category_id": 12 },
  { "id": 28, "name": "베이킹소다", "unit_id": 1, "price": 56.25, "category_id": 10 },
  { "id": 29, "name": "베이킹파우더", "unit_id": 1, "price": 117.75, "category_id": 10 },
  { "id": 30, "name": "부침가루", "unit_id": 11, "price": 798, "category_id": 4 },
  { "id": 31, "name": "분유", "unit_id": 3, "price": 26.04, "category_id": 12 },
  { "id": 32, "name": "빵", "unit_id": 5, "price": 76.5, "category_id": 9 },
  { "id": 33, "name": "생강가루", "unit_id": 3, "price": 13.63, "category_id": 10 },
  { "id": 34, "name": "설탕", "unit_id": 3, "price": 5.89, "category_id": 10 },
  { "id": 35, "name": "소금", "unit_id": 1, "price": 99.15, "category_id": 10 },
  { "id": 36, "name": "스파게티면", "unit_id": 3, "price": 5.48, "category_id": 4 },
  { "id": 37, "name": "시나몬가루", "unit_id": 3, "price": 2.4, "category_id": 10 },
  { "id": 38, "name": "식빵", "unit_id": 12, "price": 86.5, "category_id": 9 },
  { "id": 39, "name": "식용유", "unit_id": 11, "price": 722, "category_id": 10 },
  { "id": 40, "name": "쌀뜨물", "unit_id": 11, "price": 0, "category_id": 2 },
  { "id": 41, "name": "양파", "unit_id": 5, "price": 540, "category_id": 1 },
  { "id": 42, "name": "연유", "unit_id": 1, "price": 83.4, "category_id": 12 },
  { "id": 43, "name": "옥수수통조림", "unit_id": 13, "price": 591.6, "category_id": 9 },
  { "id": 44, "name": "올리고당", "unit_id": 1, "price": 277.8, "category_id": 10 },
  { "id": 45, "name": "올리브유", "unit_id": 1, "price": 540, "category_id": 10 },
  { "id": 46, "name": "우유", "unit_id": 3, "price": 4.61, "category_id": 12 },
  { "id": 47, "name": "육수", "unit_id": 11, "price": 0, "category_id": 10 },
  { "id": 48, "name": "진간장", "unit_id": 1, "price": 48.6, "category_id": 10 },
  { "id": 49, "name": "참치", "unit_id": 13, "price": 268.5, "category_id": 8 },
  { "id": 50, "name": "참치액", "unit_id": 1, "price": 15.75, "category_id": 10 },
  { "id": 51, "name": "찹쌀가루", "unit_id": 3, "price": 7.4, "category_id": 2 },
  { "id": 52, "name": "채소", "unit_id": 1, "price": 179.4, "category_id": 1 },
  { "id": 53, "name": "청양고추", "unit_id": 5, "price": 238, "category_id": 1 },
  { "id": 54, "name": "청주", "unit_id": 1, "price": 92.7, "category_id": 10 },
  { "id": 55, "name": "카놀라유", "unit_id": 1, "price": 193.5, "category_id": 10 },
  { "id": 56, "name": "카레가루", "unit_id": 1, "price": 34.75, "category_id": 10 },
  { "id": 57, "name": "크랜베리", "unit_id": 9, "price": 1152.9, "category_id": 13 },
  { "id": 58, "name": "통깨", "unit_id": 3, "price": 28.15, "category_id": 6 },
  { "id": 59, "name": "파슬리가루", "unit_id": 1, "price": 195, "category_id": 1 },
  { "id": 60, "name": "파프리카", "unit_id": 5, "price": 841.4, "category_id": 1 },
  { "id": 61, "name": "팽이버섯", "unit_id": 14, "price": 1000, "category_id": 29 },
  { "id": 62, "name": "표고버섯", "unit_id": 5, "price": 396, "category_id": 29 },
  { "id": 63, "name": "피망", "unit_id": 5, "price": 1188, "category_id": 1 },
  { "id": 64, "name": "피자치즈", "unit_id": 11, "price": 222, "category_id": 12 },
  { "id": 65, "name": "햄", "unit_id": 15, "price": 36.3, "category_id": 9 },
  { "id": 66, "name": "후추", "unit_id": 3, "price": 7.92, "category_id": 10 },
  { "id": 67, "name": "계란노른자", "unit_id": 5, "price": 133, "category_id": 12 },
  { "id": 68, "name": "고추", "unit_id": 5, "price": 119, "category_id": 1 },
  { "id": 69, "name": "계란흰자", "unit_id": 5, "price": 133, "category_id": 12 },
  { "id": 70, "name": "고춧가루", "unit_id": 1, "price": 940, "category_id": 10 },
  { "id": 71, "name": "과일", "unit_id": 5, "price": 636, "category_id": 13 },
  { "id": 72, "name": "굴", "unit_id": 5, "price": 170, "category_id": 8 },
  { "id": 73, "name": "굴소스", "unit_id": 1, "price": 168, "category_id": 10 },
  { "id": 74, "name": "귤", "unit_id": 3, "price": 3, "category_id": 13 },
  { "id": 75, "name": "김치", "unit_id": 16, "price": 11370, "category_id": 9 },
  { "id": 76, "name": "김치국물", "unit_id": 11, "price": 0, "category_id": 9 },
  { "id": 77, "name": "깨", "unit_id": 3, "price": 76, "category_id": 6 },
  { "id": 78, "name": "깻잎", "unit_id": 18, "price": 21, "category_id": 1 },
  { "id": 79, "name": "꼬막", "unit_id": 17, "price": 3160, "category_id": 8 },
  { "id": 80, "name": "꽁치", "unit_id": 13, "price": 7200, "category_id": 8 },
  { "id": 81, "name": "상추", "unit_id": 18, "price": 203, "category_id": 1 },
  { "id": 82, "name": "나빠주", "unit_id": 1, "price": 120, "category_id": 1 },
  { "id": 83, "name": "냉동딸기", "unit_id": 11, "price": 774, "category_id": 13 },
  { "id": 84, "name": "다시마", "unit_id": 18, "price": 261, "category_id": 5 },
  { "id": 85, "name": "꿀", "unit_id": 1, "price": 325, "category_id": 10 },
  { "id": 86, "name": "다시다", "unit_id": 1, "price": 287, "category_id": 10 },
  { "id": 87, "name": "다진생강", "unit_id": 1, "price": 265, "category_id": 10 },
  { "id": 88, "name": "다진양파", "unit_id": 5, "price": 432, "category_id": 10 },
  { "id": 89, "name": "당면", "unit_id": 9, "price": 745, "category_id": 4 },
  { "id": 90, "name": "돼지고기", "unit_id": 3, "price": 30, "category_id": 11 },
  { "id": 91, "name": "된장", "unit_id": 1, "price": 61, "category_id": 10 },
  { "id": 92, "name": "두반장", "unit_id": 1, "price": 233, "category_id": 10 },
  { "id": 93, "name": "드레싱", "unit_id": 14, "price": 1035, "category_id": 10 },
  { "id": 94, "name": "들기름", "unit_id": 1, "price": 76, "category_id": 10 },
  { "id": 95, "name": "딸기", "unit_id": 5, "price": 123, "category_id": 13 },
  { "id": 96, "name": "땅콩", "unit_id": 3, "price": 0, "category_id": 6 },
  { "id": 97, "name": "떡볶이떡", "unit_id": 3, "price": 8, "category_id": 9 },
  { "id": 98, "name": "또띠아", "unit_id": 18, "price": 594, "category_id": 9 },
  { "id": 99, "name": "라면사리", "unit_id": 17, "price": 558, "category_id": 9 },
  { "id": 100, "name": "레몬즙", "unit_id": 1, "price": 744, "category_id": 10 }
]

